snapconfig-0.8.0.dist-info/METADATA
snapconfig-0.8.0.dist-info/WHEEL
snapconfig-0.8.0.dist-info/licenses/LICENSE
snapconfig/__init__.py
snapconfig/snapconfig.cpython-313-darwin.so
snapconfig-0.8.0.dist-info/RECORD
