Metadata-Version: 2.4
Name: snapconfig
Version: 0.8.0
Classifier: Development Status :: 4 - Beta
Classifier: Intended Audience :: Developers
Classifier: License :: OSI Approved :: MIT License
Classifier: Programming Language :: Python :: 3
Classifier: Programming Language :: Python :: 3.8
Classifier: Programming Language :: Python :: 3.9
Classifier: Programming Language :: Python :: 3.10
Classifier: Programming Language :: Python :: 3.11
Classifier: Programming Language :: Python :: 3.12
Classifier: Programming Language :: Python :: 3.13
Classifier: Programming Language :: Rust
Classifier: Topic :: Software Development :: Libraries
Requires-Dist: pytest ; extra == 'dev'
Requires-Dist: pyyaml ; extra == 'dev'
Provides-Extra: dev
License-File: LICENSE
Summary: Superfast config loader for Python, powered by Rust + rkyv
Keywords: config,json,yaml,toml,ini,dotenv,fast,zero-copy,cache,rkyv
License: MIT
Requires-Python: >=3.8
